dc_qiskit_algorithms/ControlledStatePreparation.py
dc_qiskit_algorithms/DraperAdder.py
dc_qiskit_algorithms/FlipFlopQuantumRam.py
dc_qiskit_algorithms/MöttönenStatePreparation.py
dc_qiskit_algorithms/Qft.py
dc_qiskit_algorithms/UniformRotation.py
dc_qiskit_algorithms/__init__.py
dc_qiskit_algorithms/_version.py
dc_qiskit_algorithms-0.0.14.dist-info/LICENSE
dc_qiskit_algorithms-0.0.14.dist-info/METADATA
dc_qiskit_algorithms-0.0.14.dist-info/WHEEL
dc_qiskit_algorithms-0.0.14.dist-info/top_level.txt
dc_qiskit_algorithms-0.0.14.dist-info/RECORD
